README.md
setup.py
botouk/__init__.py
botouk/base.py
botouk/s3.py
botouk/sts.py
botouk.egg-info/PKG-INFO
botouk.egg-info/SOURCES.txt
botouk.egg-info/dependency_links.txt
botouk.egg-info/requires.txt
botouk.egg-info/top_level.txt
test/test_main.py