Metadata-Version: 1.2
Name: botouk
Version: 0.0.0
Summary: Boto Wrapper
Home-page: https://github.com/ukwksk/botouk
Author: ukwksk
Author-email: pylibs@ukwksk.co
Maintainer: ukwksk
Maintainer-email: pylibs@ukwksk.co
License: MIT
Keywords: AWS Boto3
Platform: UNKNOWN
Classifier: Programming Language :: Python :: 3.6
Classifier: License :: OSI Approved :: MIT License
Requires-Python: >=3.6
